autologpy/__init__.py
autologpy-0.0.1.dist-info/METADATA
autologpy-0.0.1.dist-info/WHEEL
autologpy-0.0.1.dist-info/top_level.txt
autologpy-0.0.1.dist-info/RECORD
