Metadata-Version: 2.1
Name: autologpy
Version: 0.0.1
Summary: A python package that allows you to log the time of an action and save any movement.
Author-email: pandaxyzzz <pandaxyz@tourble.org>
Project-URL: Homepage, https://github.com/Pandaxyzzz/AutologPY
Project-URL: Bug Tracker, https://github.com/Pandaxyzzz/AutologPY/issues
Classifier: Programming Language :: Python :: 3
Classifier: License :: OSI Approved :: MIT License
Classifier: Operating System :: OS Independent
Requires-Python: >=3.7
